LICENSE
MANIFEST.in
setup.py
hotmic.egg-info/PKG-INFO
hotmic.egg-info/SOURCES.txt
hotmic.egg-info/dependency_links.txt
hotmic.egg-info/top_level.txt
lib/__init__.py
lib/polynomials.py