Metadata-Version: 1.1
Name: hotmic
Version: 0.1.7
Summary: A Galois LFSR implementation with lots of polys.
Home-page: https://github.com/frank2/hotmic
Author: frank2
Author-email: frank2@dc949.org
License: GPLv3
Keywords: lfsr
Platform: UNKNOWN
Classifier: Development Status :: 3 - Alpha
Classifier: Topic :: Software Development :: Libraries
Classifier: License :: OSI Approved :: GNU General Public License v3 (GPLv3)
